clinicore/__init__.py
clinicore/models.py
clinicore/migrations/0001_initial.py
clinicore/migrations/0002_biosample_patient_biosample_project.py
clinicore/migrations/0003_alter_project_uid.py
clinicore/migrations/0004_remove_biosample_project_clinicaltrial_and_more.py
clinicore/migrations/0005_alter_biosample_created_by_alter_biosample_run_and_more.py
clinicore/migrations/0006_artifactbiosample_artifactclinicaltrial_and_more.py
clinicore/migrations/0007_alter_artifactbiosample_artifact_and_more.py
clinicore/migrations/0008_lamindbv1.py
clinicore/migrations/0009_alter_biosample_space_alter_clinicaltrial_space_and_more.py
clinicore/migrations/0010_rename_aux_biosample__aux_and_more.py
clinicore/migrations/0011_alter_biosample__aux_alter_clinicaltrial__aux_and_more.py
clinicore/migrations/0012_lamindbv1_part6.py
clinicore/migrations/0013_alter_biosample_artifacts.py
clinicore/migrations/0014_alter_artifactbiosample_options_and_more.py
clinicore/migrations/__init__.py
clinicore-1.2.1.dist-info/LICENSE
clinicore-1.2.1.dist-info/WHEEL
clinicore-1.2.1.dist-info/METADATA
clinicore-1.2.1.dist-info/RECORD
