Metadata-Version: 2.3
Name: clinicore
Version: 1.2.1
Summary: Basic clinical entities [`source <https://github.com/laminlabs/clinicore/blob/main/clinicore/models.py>`__].
Author-email: Lamin Labs <open-source@lamin.ai>
Requires-Dist: lamindb[bionty]>=1.6a1,<2
Requires-Dist: pre-commit ; extra == "dev"
Requires-Dist: nox ; extra == "dev"
Requires-Dist: pytest>=8.3.3 ; extra == "dev"
Requires-Dist: pytest-cov ; extra == "dev"
Requires-Dist: nbproject_test ; extra == "dev"
Project-URL: Home, https://github.com/laminlabs/clinicore
Provides-Extra: dev
